topologyx/main.py
topologyx/channels/__init__.py
topologyx/channels/silhouette.py
topologyx/clustering/__init__.py
topologyx/clustering/unionfind.py
topologyx/clustering/utils.py
topologyx/filtrations/__init__.py
topologyx/filtrations/utils.py
topologyx-1.2.0.dist-info/METADATA
topologyx-1.2.0.dist-info/WHEEL
topologyx-1.2.0.dist-info/entry_points.txt
topologyx-1.2.0.dist-info/licenses/LICENSE
topologyx-1.2.0.dist-info/RECORD
