Metadata-Version: 2.4
Name: topologyx
Version: 1.2.0
Summary: Topology data analysis routines
Project-URL: Homepage, https://github.com/merylldindin/topologyx
Project-URL: Repository, https://github.com/merylldindin/topologyx
Author-email: Meryll Dindin <merylldin@gmail.com>
License: Apache-2.0
License-File: LICENSE
Classifier: Development Status :: 4 - Beta
Classifier: Intended Audience :: Developers
Classifier: License :: OSI Approved :: Apache Software License
Classifier: Programming Language :: Python :: 3.13
Requires-Python: >=3.13
Requires-Dist: gudhi>=3.10.0
Requires-Dist: keras>=3.0.0
Requires-Dist: matplotlib>=3.8.0
Requires-Dist: numpy>=1.26.0
Requires-Dist: plotly>=5.18.0
Requires-Dist: scikit-learn>=1.4.0
Requires-Dist: tqdm>=4.66.0
